safe_reboot/__init__.py
safe_reboot/safe_reboot.py
safe_reboot-0.2.1.dist-info/AUTHORS.rst
safe_reboot-0.2.1.dist-info/LICENSE
safe_reboot-0.2.1.dist-info/METADATA
safe_reboot-0.2.1.dist-info/WHEEL
safe_reboot-0.2.1.dist-info/entry_points.txt
safe_reboot-0.2.1.dist-info/top_level.txt
safe_reboot-0.2.1.dist-info/RECORD
