Metadata-Version: 2.1
Name: safe-reboot
Version: 0.2.1
Summary: Wrapper around reboot. Checks if other users are logged in or have active screen or tmux sessions.
Home-page: https://github.com/swallat/safe_reboot
Author: Sebastian Wallat
Author-email: devwallat@gmail.com
License: Apache Software License 2.0
Keywords: safe_reboot
Platform: UNKNOWN
Classifier: Development Status :: 2 - Pre-Alpha
Classifier: Intended Audience :: Developers
Classifier: License :: OSI Approved :: Apache Software License
Classifier: Natural Language :: English
Classifier: Programming Language :: Python :: 3
Classifier: Programming Language :: Python :: 3.5
Classifier: Programming Language :: Python :: 3.6
Classifier: Programming Language :: Python :: 3.7
Classifier: Programming Language :: Python :: 3.8
Requires-Python: >=3.5
Requires-Dist: Click (>=7.0)
